panvas/__init__.py
panvas-0.0.10.dist-info/LICENSE
panvas-0.0.10.dist-info/METADATA
panvas-0.0.10.dist-info/WHEEL
panvas-0.0.10.dist-info/top_level.txt
panvas-0.0.10.dist-info/RECORD
