Metadata-Version: 2.1
Name: panvas
Version: 0.0.10
Summary: My short description for my project.
Home-page: https://github.com/franceme/panvas
Author: Miles Frantz
Author-email: frantzme@vt.edu
Classifier: Programming Language :: Python
Classifier: Programming Language :: Python :: 3
Classifier: Programming Language :: Python :: 3.8
Requires-Python: >=3.8.0
License-File: LICENSE
Requires-Dist: canvasapi
Requires-Dist: mystring
Requires-Dist: tqdm
Provides-Extra: all
